A_GIS/__init__.py
A_GIS/__main__.py
A_GIS/Code/__init__.py
A_GIS/Code/Docstring/__init__.py
A_GIS/Code/Docstring/get/__init__.py
A_GIS/Code/Docstring/modify/__init__.py
A_GIS/Code/Tree/__init__.py
A_GIS/Code/Tree/get/__init__.py
A_GIS/Code/Tree/print/__init__.py
A_GIS/Code/Tree/recurse/__init__.py
A_GIS/Code/Tree/update/__init__.py
A_GIS/Code/distill/__init__.py
A_GIS/Code/format/__init__.py
A_GIS/Data/__init__.py
A_GIS/Data/Json/__init__.py
A_GIS/Data/Json/read/__init__.py
A_GIS/Data/Llm/__init__.py
A_GIS/Data/Llm/_helpers/__init__.py
A_GIS/Data/Llm/_helpers/download_model_files/__init__.py
A_GIS/Data/Llm/_helpers/get_download_links/__init__.py
A_GIS/Data/Llm/_helpers/get_output_folder/__init__.py
A_GIS/Data/Llm/_helpers/parse_download_cli_args/__init__.py
A_GIS/Data/Llm/_helpers/sanitize_model_and_branch_names/__init__.py
A_GIS/Data/Llm/_helpers/start_download_threads/__init__.py
A_GIS/Data/Llm/download/__init__.py
A_GIS/File/__init__.py
A_GIS/File/Directory/__init__.py
A_GIS/File/Directory/make/__init__.py
A_GIS/File/Directory/make/tests/test_requirements.py
A_GIS/File/download/__init__.py
A_GIS/File/read/__init__.py
A_GIS/File/write/__init__.py
A_GIS/Image/__init__.py
A_GIS/Image/Metadata/__init__.py
A_GIS/Image/Metadata/get/__init__.py
A_GIS/Image/Metadata/modify/__init__.py
A_GIS/Image/Metadata/remove/__init__.py
A_GIS/Image/Metadata/remove/tests/__init__.py
A_GIS/Image/Metadata/remove/tests/test_requirements.py
A_GIS/Image/new/__init__.py
A_GIS/Image/open/__init__.py
A_GIS/Image/validate/__init__.py
A_GIS/Math/__init__.py
A_GIS/Math/Statistics/__init__.py
A_GIS/Math/Statistics/CorrelationMatrix/__init__.py
A_GIS/Math/Statistics/CorrelationMatrix/from_numpy/__init__.py
A_GIS/Math/Statistics/CorrelationMatrix/from_samples/__init__.py
A_GIS/Math/Statistics/CorrelationMatrix/new/__init__.py
A_GIS/Math/Statistics/CorrelationMatrix/to_numpy/__init__.py
A_GIS/Math/Statistics/Distribution/__init__.py
A_GIS/Math/Statistics/Distribution/Triangular/__init__.py
A_GIS-0.8.1.dist-info/LICENSE
A_GIS-0.8.1.dist-info/METADATA
A_GIS-0.8.1.dist-info/WHEEL
A_GIS-0.8.1.dist-info/entry_points.txt
A_GIS-0.8.1.dist-info/top_level.txt
A_GIS-0.8.1.dist-info/RECORD
