Metadata-Version: 2.1
Name: A_GIS
Version: 0.8.1
Summary: Functional python that shields users from breaking changes.
Author-email: AEGIS 001 <a-gis-001@proton.me>
License: This is free and unencumbered software released into the public domain.
Project-URL: documentation, https://a-gis.readthedocs.io
Project-URL: bug-tracker, https://github.com/a-gis-001/a-gis/issues
Project-URL: source, https://github.com/a-gis-001/a-gis
Keywords: art,AI
Classifier: Development Status :: 3 - Alpha
Classifier: Intended Audience :: Developers
Classifier: Topic :: Software Development :: Libraries
Classifier: Programming Language :: Python :: 3 :: Only
Classifier: License :: OSI Approved :: The Unlicense (Unlicense)
Classifier: Operating System :: OS Independent
Requires-Python: >=3.10
License-File: LICENSE
Requires-Dist: click
Requires-Dist: matplotlib
Requires-Dist: scipy
Requires-Dist: numpy
Requires-Dist: pydantic
